{
  "blocks": [
    {
      "template": "header-mobile-block-top-navigation",
      "links": [
        {
          "label": "HDPE Capabilities",
          "megaMenu": false,
          "page": ".forestry/content/pages/capabilities.json"
        },
        {
          "label": "",
          "page": [

          ],
          "megaMenu": false
        },
        {
          "label": "",
          "page": [

          ],
          "megaMenu": false
        },
        {
          "label": "",
          "page": [

          ],
          "megaMenu": false
        }
      ]
    }
  ]
}
