{
  "title": "About",
  "type": "page",
  "slug": "",
  "rows": [
    {
      "label": "Hero Row",
      "columns": [
        {
          "label": "Hero Column",
          "blocks": [
            {
              "template": "main-hero"
            }
          ]
        }
      ]
    }
  ],
  "blocks": [
    {
      "template": "main-hero",
      "image": "/.forestry/content/images/about.png",
      "button": false,
      "buttonLink": [

      ],
      "text": [
        {
          "element": "Heading 1",
          "text": "A FUSION OF QUALITY AND KNOW-HOW"
        }
      ],
      "buttonText": "\"\"",
      "video": "",
      "buttonIcon": ""
    },
    {
      "template": "main-blank"
    }
  ]
}
