{
  "title": "Account",
  "type": "page",
  "slug": "",
  "rows": [

  ],
  "blocks": [
    {
      "template": "main-conditional-content",
      "conditionalBlocks": [
        {
          "state": "register",
          "block": [
            {
              "template": "main-create-account",
              "title": "New Account",
              "text": "Thank you for creating an account with us so we can serve you better.",
              "columns": [
                {
                  "rows": [
                    {
                      "fields": [
                        {
                          "label": "First Name",
                          "icon": "/.forestry/content/images/user.svg",
                          "type": "Text"
                        }
                      ]
                    },
                    {
                      "fields": [
                        {
                          "label": "Last Name",
                          "icon": "/.forestry/content/images/user.svg",
                          "type": "Text"
                        }
                      ]
                    },
                    {
                      "fields": [
                        {
                          "label": "Email address",
                          "icon": "/.forestry/content/images/placeholder.png",
                          "type": "Text"
                        }
                      ]
                    },
                    {
                      "fields": [
                        {
                          "label": "Phone Number",
                          "icon": "/.forestry/content/images/phone.svg",
                          "type": "Text"
                        }
                      ]
                    }
                  ]
                },
                {
                  "rows": [
                    {
                      "fields": [
                        {
                          "label": "Company Name",
                          "icon": "/.forestry/content/images/users.svg",
                          "type": "Text"
                        }
                      ]
                    },
                    {
                      "fields": [
                        {
                          "label": "City",
                          "icon": "/.forestry/content/images/location.svg",
                          "type": "Text"
                        },
                        {
                          "label": "State",
                          "icon": "/.forestry/content/images/location.svg",
                          "type": "Text"
                        }
                      ]
                    },
                    {
                      "fields": [
                        {
                          "label": "Password",
                          "icon": "/.forestry/content/images/password.svg",
                          "type": "Password"
                        }
                      ]
                    },
                    {
                      "fields": [
                        {
                          "label": "Confirm Password",
                          "icon": "/.forestry/content/images/password.svg",
                          "type": "Password"
                        }
                      ]
                    }
                  ]
                }
              ]
            }
          ]
        }
      ]
    },
    {
      "template": "main-account"
    }
  ]
}
